.DS_Store
flaskr/__init__.py
flaskr/action/__init__.py
flaskr/action/comment_action.py
flaskr/action/user_action.py
flaskr/action/video_action.py
flaskr/model/__init__.py
flaskr/model/comment.py
flaskr/model/user.py
flaskr/model/video.py
tests/__init__.py
tests/conftest.py
tests/test_change_description.py
tests/test_change_password.py
tests/test_change_title.py
tests/test_comment.py
tests/test_login.py
tests/test_register.py
tests/test_user_detail.py
tests/test_video_detail.py
tests/test_video_list.py
tests/test_video_my_list.py
tests/test_video_upload.py
VAT_package-0.0.2.dist-info/METADATA
VAT_package-0.0.2.dist-info/WHEEL
VAT_package-0.0.2.dist-info/top_level.txt
VAT_package-0.0.2.dist-info/RECORD
